irv/__init__.py
irv/__main__.py
irv/ballots.py
irv/constants.py
irv/env.py
irv/irv.py
wildcat_connection/__init__.py
wildcat_connection/constants.py
wildcat_connection/csv.py
wildcat_connection/env.py
wildcat_connection/utils.py
slivka_irv-1.1.3.dist-info/LICENSE
slivka_irv-1.1.3.dist-info/METADATA
slivka_irv-1.1.3.dist-info/WHEEL
slivka_irv-1.1.3.dist-info/entry_points.txt
slivka_irv-1.1.3.dist-info/top_level.txt
slivka_irv-1.1.3.dist-info/RECORD
